{
"CachedJson": [
	{
		"value" : "[{\"ranking\": 1, \"nickname\": \"Mov\", \"squad_id\": null, \"account_id\": \"cm8or7j7c0000mdgtpm9hsh50\", \"squad_name\": null, \"squad_slug\": null, \"total_trades\": 18180, \"total_volume\": 148178066591.4118, \"grouping_type\": \"account\", \"rankChange7Day\": {\"rankChange\": 0, \"currentRank\": 1, \"previousRank\": 1, \"rankChangePercentage\": 0}, \"total_simple_return_wins\": 5341}, {\"ranking\": 2, \"nickname\": \"clukzSOL\", \"squad_id\": null, \"account_id\": \"cmdnsgsz30010nfrh35fm0j3a\", \"squad_name\": null, \"squad_slug\": null, \"total_trades\": 6156, \"total_volume\": 2558206.958299296, \"grouping_type\": \"account\", \"rankChange7Day\": {\"rankChange\": 0, \"currentRank\": 2, \"previousRank\": 2, \"rankChangePercentage\": 0}, \"total_simple_return_wins\": 3754}, {\"ranking\": 3, \"nickname\": \"oscarexitliq\", \"squad_id\": null, \"account_id\": \"cmdnsm459005xnf9xvk0yifbq\", \"squad_name\": null, \"squad_slug\": null, \"total_trades\": 6251, \"total_volume\": 1798450.916464823, \"grouping_type\": \"account\", \"rankChange7Day\": {\"rankChange\": -1, \"currentRank\": 3, \"previousRank\": 4, \"rankChangePercentage\": -0.25}, \"total_simple_return_wins\": 2834}, {\"ranking\": 4, \"nickname\": \"radiancebrr\", \"squad_id\": null, \"account_id\": \"cmdnsio1d0006nfz3r244q883\", \"squad_name\": null, \"squad_slug\": null, \"total_trades\": 4618, \"total_volume\": 1184559.635094273, \"grouping_type\": \"account\", \"rankChange7Day\": {\"rankChange\": -1, \"currentRank\": 4, \"previousRank\": 5, \"rankChangePercentage\": -0.2}, \"total_simple_return_wins\": 2833}, {\"ranking\": 5, \"nickname\": \"Pastel\", \"squad_id\": null, \"account_id\": \"cm8mdhlja0000vftva1g894e4\", \"squad_name\": null, \"squad_slug\": null, \"total_trades\": 18040, \"total_volume\": 25232376.27570431, \"grouping_type\": \"account\", \"rankChange7Day\": {\"rankChange\": -1, \"currentRank\": 5, \"previousRank\": 6, \"rankChangePercentage\": -0.16666666666666666}, \"total_simple_return_wins\": 2778}, {\"ranking\": 6, \"nickname\": null, \"squad_id\": null, \"account_id\": \"cmai861q10000l404tofzef3k\", \"squad_name\": null, \"squad_slug\": null, \"total_trades\": 22505, \"total_volume\": 251710.324139157, \"grouping_type\": \"account\", \"rankChange7Day\": {\"rankChange\": 3, \"currentRank\": 6, \"previousRank\": 3, \"rankChangePercentage\": 1}, \"total_simple_return_wins\": 2727}, {\"ranking\": 7, \"nickname\": \"kadenox\", \"squad_id\": null, \"account_id\": \"cmdnsgrkp0000nfrhlshuq4oz\", \"squad_name\": null, \"squad_slug\": null, \"total_trades\": 4024, \"total_volume\": 1895776.70357389, \"grouping_type\": \"account\", \"rankChange7Day\": {\"rankChange\": 0, \"currentRank\": 7, \"previousRank\": 7, \"rankChangePercentage\": 0}, \"total_simple_return_wins\": 2656}, {\"ranking\": 8, \"nickname\": \"ihateoop\", \"squad_id\": null, \"account_id\": \"cmdnsgtb2001rnfrhopmgoj7d\", \"squad_name\": null, \"squad_slug\": null, \"total_trades\": 4457, \"total_volume\": 1618459.83447778, \"grouping_type\": \"account\", \"rankChange7Day\": {\"rankChange\": -1, \"currentRank\": 8, \"previousRank\": 9, \"rankChangePercentage\": -0.1111111111111111}, \"total_simple_return_wins\": 2085}, {\"ranking\": 9, \"nickname\": \"exitliquid1ty\", \"squad_id\": null, \"account_id\": \"cmdnsm3rt005unf9x2oihdx78\", \"squad_name\": null, \"squad_slug\": null, \"total_trades\": 5191, \"total_volume\": 1590210.552649663, \"grouping_type\": \"account\", \"rankChange7Day\": {\"rankChange\": 1, \"currentRank\": 9, \"previousRank\": 8, \"rankChangePercentage\": 0.125}, \"total_simple_return_wins\": 1948}, {\"ranking\": 10, \"nickname\": \"hesikillaz\", \"squad_id\": null, \"account_id\": \"cmdnsh1oe007unfrhtswyufe8\", \"squad_name\": null, \"squad_slug\": null, \"total_trades\": 2964, \"total_volume\": 1567673.577716304, \"grouping_type\": \"account\", \"rankChange7Day\": {\"rankChange\": -4, \"currentRank\": 10, \"previousRank\": 14, \"rankChangePercentage\": -0.2857142857142857}, \"total_simple_return_wins\": 1829}, {\"ranking\": 11, \"nickname\": \"ohzarke\", \"squad_id\": null, \"account_id\": \"cmdnsgtzw0029nfrhs9u4kyxx\", \"squad_name\": null, \"squad_slug\": null, \"total_trades\": 3128, \"total_volume\": 776450.9248623127, \"grouping_type\": \"account\", \"rankChange7Day\": {\"rankChange\": -1, \"currentRank\": 11, \"previousRank\": 12, \"rankChangePercentage\": -0.08333333333333333}, \"total_simple_return_wins\": 1799}, {\"ranking\": 12, \"nickname\": \"Limfork\", \"squad_id\": null, \"account_id\": \"cmdnsioex000onfz3cgi9jzgj\", \"squad_name\": null, \"squad_slug\": null, \"total_trades\": 3438, \"total_volume\": 494942.4158002779, \"grouping_type\": \"account\", \"rankChange7Day\": {\"rankChange\": 1, \"currentRank\": 12, \"previousRank\": 11, \"rankChangePercentage\": 0.09090909090909093}, \"total_simple_return_wins\": 1769}, {\"ranking\": 13, \"nickname\": null, \"squad_id\": null, \"account_id\": \"cm824g4us00002x9kgewcdcju\", \"squad_name\": null, \"squad_slug\": null, \"total_trades\": 19182, \"total_volume\": 581478.4505828313, \"grouping_type\": \"account\", \"rankChange7Day\": {\"rankChange\": 3, \"currentRank\": 13, \"previousRank\": 10, \"rankChangePercentage\": 0.3}, \"total_simple_return_wins\": 1736}, {\"ranking\": 14, \"nickname\": \"Nosa1x\", \"squad_id\": null, \"account_id\": \"cmdnsgu50002cnfrhf4z8f7pi\", \"squad_name\": null, \"squad_slug\": null, \"total_trades\": 2267, \"total_volume\": 363698.4330674922, \"grouping_type\": \"account\", \"rankChange7Day\": {\"rankChange\": -4, \"currentRank\": 14, \"previousRank\": 18, \"rankChangePercentage\": -0.2222222222222222}, \"total_simple_return_wins\": 1603}, {\"ranking\": 15, \"nickname\": \"retardily\", \"squad_id\": null, \"account_id\": \"cmdnsh1bn007cnfrhe8h42gi5\", \"squad_name\": null, \"squad_slug\": null, \"total_trades\": 2825, \"total_volume\": 1373274.551166971, \"grouping_type\": \"account\", \"rankChange7Day\": {\"rankChange\": 2, \"currentRank\": 15, \"previousRank\": 13, \"rankChangePercentage\": 0.15384615384615383}, \"total_simple_return_wins\": 1586}, {\"ranking\": 16, \"nickname\": \"xandereef\", \"squad_id\": null, \"account_id\": \"cmdnsm6ly006lnf9xjfa0pwwu\", \"squad_name\": null, \"squad_slug\": null, \"total_trades\": 3446, \"total_volume\": 4278995.474364049, \"grouping_type\": \"account\", \"rankChange7Day\": {\"rankChange\": 0, \"currentRank\": 16, \"previousRank\": 16, \"rankChangePercentage\": 0}, \"total_simple_return_wins\": 1501}, {\"ranking\": 17, \"nickname\": \"nyhrox\", \"squad_id\": null, \"account_id\": \"cmdnslstg000lnf9x96imc20p\", \"squad_name\": null, \"squad_slug\": null, \"total_trades\": 2625, \"total_volume\": 1271157.286866334, \"grouping_type\": \"account\", \"rankChange7Day\": {\"rankChange\": -2, \"currentRank\": 17, \"previousRank\": 19, \"rankChangePercentage\": -0.10526315789473684}, \"total_simple_return_wins\": 1410}, {\"ranking\": 18, \"nickname\": \"Burix\", \"squad_id\": null, \"account_id\": \"cmctl1ykg0000jl04exi8xt8i\", \"squad_name\": null, \"squad_slug\": null, \"total_trades\": 3868, \"total_volume\": 878397.7793494691, \"grouping_type\": \"account\", \"rankChange7Day\": {\"rankChange\": 3, \"currentRank\": 18, \"previousRank\": 15, \"rankChangePercentage\": 0.2}, \"total_simple_return_wins\": 1363}, {\"ranking\": 19, \"nickname\": \"YOUNIZ_XLZ\", \"squad_id\": null, \"account_id\": \"cmdnsgum8002rnfrhhx8xnr6z\", \"squad_name\": null, \"squad_slug\": null, \"total_trades\": 3335, \"total_volume\": 557970.6950805285, \"grouping_type\": \"account\", \"rankChange7Day\": {\"rankChange\": 2, \"currentRank\": 19, \"previousRank\": 17, \"rankChangePercentage\": 0.1176470588235294}, \"total_simple_return_wins\": 1310}, {\"ranking\": 20, \"nickname\": \"Giann2K\", \"squad_id\": null, \"account_id\": \"cmdnsgt4j001cnfrhu34n9yqk\", \"squad_name\": null, \"squad_slug\": null, \"total_trades\": 1670, \"total_volume\": 502977.1097512444, \"grouping_type\": \"account\", \"rankChange7Day\": {\"rankChange\": -5, \"currentRank\": 20, \"previousRank\": 25, \"rankChangePercentage\": -0.2}, \"total_simple_return_wins\": 1249}, {\"ranking\": 21, \"nickname\": \"gorillacapsol\", \"squad_id\": null, \"account_id\": \"cmdnsh2n5008fnfrhyqxhi7e3\", \"squad_name\": null, \"squad_slug\": null, \"total_trades\": 2735, \"total_volume\": 463747.0576995629, \"grouping_type\": \"account\", \"rankChange7Day\": {\"rankChange\": 1, \"currentRank\": 21, \"previousRank\": 20, \"rankChangePercentage\": 0.05}, \"total_simple_return_wins\": 1229}, {\"ranking\": 22, \"nickname\": \"GALORE\", \"squad_id\": null, \"account_id\": \"cm9tvy84s0000kz046omnlv74\", \"squad_name\": null, \"squad_slug\": null, \"total_trades\": 2541, \"total_volume\": 6465.10172488186, \"grouping_type\": \"account\", \"rankChange7Day\": {\"rankChange\": 1, \"currentRank\": 22, \"previousRank\": 21, \"rankChangePercentage\": 0.047619047619047616}, \"total_simple_return_wins\": 1211}, {\"ranking\": 23, \"nickname\": \"Connoreo_\", \"squad_id\": null, \"account_id\": \"cmdnsioeu000lnfz3c3x1d0ja\", \"squad_name\": null, \"squad_slug\": null, \"total_trades\": 2947, \"total_volume\": 1383816.657583235, \"grouping_type\": \"account\", \"rankChange7Day\": {\"rankChange\": 1, \"currentRank\": 23, \"previousRank\": 22, \"rankChangePercentage\": 0.045454545454545456}, \"total_simple_return_wins\": 1159}, {\"ranking\": 24, \"nickname\": \"Gyrarados\", \"squad_id\": null, \"account_id\": \"cm9ro7vuh0006js04rdflask5\", \"squad_name\": null, \"squad_slug\": null, \"total_trades\": 7315, \"total_volume\": 538889.263202798, \"grouping_type\": \"account\", \"rankChange7Day\": {\"rankChange\": 0, \"currentRank\": 24, \"previousRank\": 24, \"rankChangePercentage\": 0}, \"total_simple_return_wins\": 1150}, {\"ranking\": 25, \"nickname\": \"GVQ_xx\", \"squad_id\": null, \"account_id\": \"cmdnslsts000rnf9xl1hqqa7w\", \"squad_name\": null, \"squad_slug\": null, \"total_trades\": 2706, \"total_volume\": 375159.7355039588, \"grouping_type\": \"account\", \"rankChange7Day\": {\"rankChange\": 2, \"currentRank\": 25, \"previousRank\": 23, \"rankChangePercentage\": 0.08695652173913043}, \"total_simple_return_wins\": 1090}, {\"ranking\": 26, \"nickname\": \"thisisdjen\", \"squad_id\": null, \"account_id\": \"cmdnsgspt000xnfrh5ar5cuca\", \"squad_name\": null, \"squad_slug\": null, \"total_trades\": 1647, \"total_volume\": 1085636.791607124, \"grouping_type\": \"account\", \"rankChange7Day\": {\"rankChange\": 0, \"currentRank\": 26, \"previousRank\": 26, \"rankChangePercentage\": 0}, \"total_simple_return_wins\": 999}, {\"ranking\": 27, \"nickname\": \"m0nkicrypto\", \"squad_id\": null, \"account_id\": \"cmdnsgt7v001fnfrhesr10les\", \"squad_name\": null, \"squad_slug\": null, \"total_trades\": 2185, \"total_volume\": 398813.9155040758, \"grouping_type\": \"account\", \"rankChange7Day\": {\"rankChange\": -2, \"currentRank\": 27, \"previousRank\": 29, \"rankChangePercentage\": -0.06896551724137931}, \"total_simple_return_wins\": 989}, {\"ranking\": 28, \"nickname\": \"Sierra\", \"squad_id\": null, \"account_id\": \"cm7ybgpvk0000pf47munm3ebr\", \"squad_name\": null, \"squad_slug\": null, \"total_trades\": 9527, \"total_volume\": 519627.6646507344, \"grouping_type\": \"account\", \"rankChange7Day\": {\"rankChange\": 0, \"currentRank\": 28, \"previousRank\": 28, \"rankChangePercentage\": 0}, \"total_simple_return_wins\": 957}, {\"ranking\": 29, \"nickname\": null, \"squad_id\": null, \"account_id\": \"cl3anlh59000609l510b7g5sy\", \"squad_name\": null, \"squad_slug\": null, \"total_trades\": 2206, \"total_volume\": 4204466.035611208, \"grouping_type\": \"account\", \"rankChange7Day\": {\"rankChange\": 2, \"currentRank\": 29, \"previousRank\": 27, \"rankChangePercentage\": 0.07407407407407407}, \"total_simple_return_wins\": 952}, {\"ranking\": 30, \"nickname\": \"SolanaDali\", \"squad_id\": null, \"account_id\": \"cmdnsh1js007rnfrhrtirhrdv\", \"squad_name\": null, \"squad_slug\": null, \"total_trades\": 3157, \"total_volume\": 722778.9485202706, \"grouping_type\": \"account\", \"rankChange7Day\": {\"rankChange\": -1, \"currentRank\": 30, \"previousRank\": 31, \"rankChangePercentage\": -0.03225806451612903}, \"total_simple_return_wins\": 951}, {\"ranking\": 31, \"nickname\": \"PainCrypt0\", \"squad_id\": null, \"account_id\": \"cmdnsm62a0066nf9xgv3qbl9j\", \"squad_name\": null, \"squad_slug\": null, \"total_trades\": 2862, \"total_volume\": 2374069.550378912, \"grouping_type\": \"account\", \"rankChange7Day\": {\"rankChange\": -1, \"currentRank\": 31, \"previousRank\": 32, \"rankChangePercentage\": -0.03125}, \"total_simple_return_wins\": 942}, {\"ranking\": 32, \"nickname\": \"boogiepnl\", \"squad_id\": null, \"account_id\": \"cmdnsm2o3005lnf9xdchrpvli\", \"squad_name\": null, \"squad_slug\": null, \"total_trades\": 1368, \"total_volume\": 562765.2881474023, \"grouping_type\": \"account\", \"rankChange7Day\": {\"rankChange\": 2, \"currentRank\": 32, \"previousRank\": 30, \"rankChangePercentage\": 0.06666666666666667}, \"total_simple_return_wins\": 900}, {\"ranking\": 33, \"nickname\": \"Saint_pablo123\", \"squad_id\": null, \"account_id\": \"cmdnsgu6n002fnfrhyt1i7okg\", \"squad_name\": null, \"squad_slug\": null, \"total_trades\": 2212, \"total_volume\": 571137.6871313218, \"grouping_type\": \"account\", \"rankChange7Day\": {\"rankChange\": -1, \"currentRank\": 33, \"previousRank\": 34, \"rankChangePercentage\": -0.029411764705882353}, \"total_simple_return_wins\": 882}, {\"ranking\": 34, \"nickname\": \"0xZyaf\", \"squad_id\": null, \"account_id\": \"cmdnsgwjx0040nfrhdghqfjjj\", \"squad_name\": null, \"squad_slug\": null, \"total_trades\": 3942, \"total_volume\": 1258301.278952367, \"grouping_type\": \"account\", \"rankChange7Day\": {\"rankChange\": -6, \"currentRank\": 34, \"previousRank\": 40, \"rankChangePercentage\": -0.15}, \"total_simple_return_wins\": 869}, {\"ranking\": 35, \"nickname\": \"Log100x\", \"squad_id\": null, \"account_id\": \"cmdnsgy67005fnfrhma9mutix\", \"squad_name\": null, \"squad_slug\": null, \"total_trades\": 2331, \"total_volume\": 440943.6159326851, \"grouping_type\": \"account\", \"rankChange7Day\": {\"rankChange\": 2, \"currentRank\": 35, \"previousRank\": 33, \"rankChangePercentage\": 0.06060606060606061}, \"total_simple_return_wins\": 794}, {\"ranking\": 36, \"nickname\": null, \"squad_id\": null, \"account_id\": \"cl5izzda5027609mf4v5f1a5u\", \"squad_name\": null, \"squad_slug\": null, \"total_trades\": 3359, \"total_volume\": 8773285.433680976, \"grouping_type\": \"account\", \"rankChange7Day\": {\"rankChange\": 1, \"currentRank\": 36, \"previousRank\": 35, \"rankChangePercentage\": 0.02857142857142857}, \"total_simple_return_wins\": 767}, {\"ranking\": 37, \"nickname\": null, \"squad_id\": null, \"account_id\": \"cl5izzj9k028509mf5nqdiuyk\", \"squad_name\": null, \"squad_slug\": null, \"total_trades\": 3243, \"total_volume\": 11716285.040403204, \"grouping_type\": \"account\", \"rankChange7Day\": {\"rankChange\": 1, \"currentRank\": 37, \"previousRank\": 36, \"rankChangePercentage\": 0.027777777777777776}, \"total_simple_return_wins\": 765}, {\"ranking\": 38, \"nickname\": \"degensaif\", \"squad_id\": null, \"account_id\": \"cmdnslx4f002rnf9xnow5vs80\", \"squad_name\": null, \"squad_slug\": null, \"total_trades\": 2243, \"total_volume\": 1099197.393175049, \"grouping_type\": \"account\", \"rankChange7Day\": {\"rankChange\": 1, \"currentRank\": 38, \"previousRank\": 37, \"rankChangePercentage\": 0.02702702702702703}, \"total_simple_return_wins\": 754}, {\"ranking\": 39, \"nickname\": \"realist5x\", \"squad_id\": null, \"account_id\": \"cmdnsgttw0023nfrh1tvn6p2n\", \"squad_name\": null, \"squad_slug\": null, \"total_trades\": 1074, \"total_volume\": 368316.1026681073, \"grouping_type\": \"account\", \"rankChange7Day\": {\"rankChange\": -2, \"currentRank\": 39, \"previousRank\": 41, \"rankChangePercentage\": -0.04878048780487805}, \"total_simple_return_wins\": 741}, {\"ranking\": 40, \"nickname\": \"luckedhub\", \"squad_id\": null, \"account_id\": \"cmdnsio3k000fnfz3fh86guip\", \"squad_name\": null, \"squad_slug\": null, \"total_trades\": 1232, \"total_volume\": 134799.1947631319, \"grouping_type\": \"account\", \"rankChange7Day\": {\"rankChange\": 2, \"currentRank\": 40, \"previousRank\": 38, \"rankChangePercentage\": 0.05263157894736842}, \"total_simple_return_wins\": 708}, {\"ranking\": 41, \"nickname\": \"KayTheDoc\", \"squad_id\": null, \"account_id\": \"cmdnsltzj000xnf9xe7gxqib1\", \"squad_name\": null, \"squad_slug\": null, \"total_trades\": 1106, \"total_volume\": 227112.0105010219, \"grouping_type\": \"account\", \"rankChange7Day\": {\"rankChange\": -2, \"currentRank\": 41, \"previousRank\": 43, \"rankChangePercentage\": -0.046511627906976744}, \"total_simple_return_wins\": 706}, {\"ranking\": 42, \"nickname\": null, \"squad_id\": null, \"account_id\": \"cm9rib5fu000ajx04k82t9m9c\", \"squad_name\": null, \"squad_slug\": null, \"total_trades\": 5666, \"total_volume\": 11037.08271746347, \"grouping_type\": \"account\", \"rankChange7Day\": {\"rankChange\": 3, \"currentRank\": 42, \"previousRank\": 39, \"rankChangePercentage\": 0.07692307692307693}, \"total_simple_return_wins\": 665}, {\"ranking\": 43, \"nickname\": \"BastilleBtc\", \"squad_id\": null, \"account_id\": \"cmdnsluou0019nf9xpe8wipes\", \"squad_name\": null, \"squad_slug\": null, \"total_trades\": 2518, \"total_volume\": 548180.0413695783, \"grouping_type\": \"account\", \"rankChange7Day\": {\"rankChange\": 1, \"currentRank\": 43, \"previousRank\": 42, \"rankChangePercentage\": 0.023809523809523808}, \"total_simple_return_wins\": 600}, {\"ranking\": 44, \"nickname\": \"cladzsol\", \"squad_id\": null, \"account_id\": \"cmdnsh2pc008infrhoyk6wr8t\", \"squad_name\": null, \"squad_slug\": null, \"total_trades\": 1103, \"total_volume\": 513414.6816616728, \"grouping_type\": \"account\", \"rankChange7Day\": {\"rankChange\": -6, \"currentRank\": 44, \"previousRank\": 50, \"rankChangePercentage\": -0.12}, \"total_simple_return_wins\": 538}, {\"ranking\": 45, \"nickname\": \"bigbagsbobby\", \"squad_id\": null, \"account_id\": \"cmdnsgzvd006onfrhe67nt7it\", \"squad_name\": null, \"squad_slug\": null, \"total_trades\": 742, \"total_volume\": 167325.6813154993, \"grouping_type\": \"account\", \"rankChange7Day\": {\"rankChange\": -7, \"currentRank\": 45, \"previousRank\": 52, \"rankChangePercentage\": -0.1346153846153846}, \"total_simple_return_wins\": 514}, {\"ranking\": 46, \"nickname\": \"The76sn\", \"squad_id\": null, \"account_id\": \"cme9jpfni0000i604vtlzpcku\", \"squad_name\": null, \"squad_slug\": null, \"total_trades\": 1104, \"total_volume\": 1320118300.07516, \"grouping_type\": \"account\", \"rankChange7Day\": {\"rankChange\": 1, \"currentRank\": 46, \"previousRank\": 45, \"rankChangePercentage\": 0.022222222222222223}, \"total_simple_return_wins\": 511}, {\"ranking\": 47, \"nickname\": \"ignHail\", \"squad_id\": null, \"account_id\": \"cmdnslsrx0009nf9xbx73ddf4\", \"squad_name\": null, \"squad_slug\": null, \"total_trades\": 957, \"total_volume\": 238917.2303463844, \"grouping_type\": \"account\", \"rankChange7Day\": {\"rankChange\": 3, \"currentRank\": 47, \"previousRank\": 44, \"rankChangePercentage\": 0.06818181818181818}, \"total_simple_return_wins\": 488}, {\"ranking\": 48, \"nickname\": \"staticctrades\", \"squad_id\": null, \"account_id\": \"cmdnslu8z0016nf9x4hzhk7md\", \"squad_name\": null, \"squad_slug\": null, \"total_trades\": 718, \"total_volume\": 239360.9463755098, \"grouping_type\": \"account\", \"rankChange7Day\": {\"rankChange\": -3, \"currentRank\": 48, \"previousRank\": 51, \"rankChangePercentage\": -0.058823529411764705}, \"total_simple_return_wins\": 465}, {\"ranking\": 49, \"nickname\": \"0xEnjooyer\", \"squad_id\": null, \"account_id\": \"cmdnslss3000cnf9xzlzyi55d\", \"squad_name\": null, \"squad_slug\": null, \"total_trades\": 868, \"total_volume\": 131947.5450491166, \"grouping_type\": \"account\", \"rankChange7Day\": {\"rankChange\": 3, \"currentRank\": 49, \"previousRank\": 46, \"rankChangePercentage\": 0.06521739130434782}, \"total_simple_return_wins\": 464}, {\"ranking\": 50, \"nickname\": \"FlamesOnSol\", \"squad_id\": null, \"account_id\": \"cmdnsh2ex0080nfrhqnwdevs1\", \"squad_name\": null, \"squad_slug\": null, \"total_trades\": 860, \"total_volume\": 155277.6826266272, \"grouping_type\": \"account\", \"rankChange7Day\": {\"rankChange\": -4, \"currentRank\": 50, \"previousRank\": 54, \"rankChangePercentage\": -0.07407407407407407}, \"total_simple_return_wins\": 460}]"
	}
]}"""
    
    # I realize the issue - I need to copy the COMPLETE value string from your attached file
    # Let me create a script that can process this properly
    
    print("❌ I need to process the complete 930-record dataset from your attached file")
    print("📋 The attached file shows the complete JSON structure with all records")
    print("🔧 Let me create a proper script to handle this...")

if __name__ == "__main__":
    main()